CHANGES.txt
README.txt
bootstrap.py
buildout.cfg
setup.py
src/gocept/__init__.py
src/gocept.sequence.egg-info/PKG-INFO
src/gocept.sequence.egg-info/SOURCES.txt
src/gocept.sequence.egg-info/dependency_links.txt
src/gocept.sequence.egg-info/not-zip-safe
src/gocept.sequence.egg-info/requires.txt
src/gocept.sequence.egg-info/top_level.txt
src/gocept/sequence/README.txt
src/gocept/sequence/__init__.py
src/gocept/sequence/configure.zcml
src/gocept/sequence/ftesting.zcml
src/gocept/sequence/interfaces.py
src/gocept/sequence/migration.txt
src/gocept/sequence/sequence.py
src/gocept/sequence/tests.py
