Metadata-Version: 1.0
Name: gocept.sequence
Version: 0.31
Summary: Generates a sequence
Home-page: http://pypi.python.org/pypi/gocept.sequence/
Author: Daniel Havlik, Sebastian Wehrmann
Author-email: dh@gocept.com
License: ZPL 2.1
Keywords: sequence generator
Platform: UNKNOWN
Classifier: Development Status :: 4 - Beta
Classifier: Environment :: Web Environment
Classifier: Intended Audience :: Developers
Classifier: License :: OSI Approved :: Zope Public License
Classifier: Programming Language :: Python
Classifier: Natural Language :: English
Classifier: Operating System :: OS Independent
Classifier: Topic :: Internet :: WWW/HTTP
